signatory/__init__.py
signatory/_impl.cp39-win_amd64.pyd
signatory/augment.py
signatory/deprecated.py
signatory/impl.py
signatory/logsignature_module.py
signatory/path.py
signatory/signature_inversion_module.py
signatory/signature_module.py
signatory/unstable.py
signatory/utility.py
signatory-1.2.6.1.9.0.dist-info/LICENSE
signatory-1.2.6.1.9.0.dist-info/METADATA
signatory-1.2.6.1.9.0.dist-info/WHEEL
signatory-1.2.6.1.9.0.dist-info/top_level.txt
signatory-1.2.6.1.9.0.dist-info/RECORD
